{"nodes": [{"id": "c_users_rahul_documents_tracko_android_app_src_main_java_com_tracko_app_ui_components_ratingbar_kt", "label": "RatingBar.kt", "file_type": "code", "source_file": "C:\\Users\\Rahul\\Documents\\Tracko\\android\\app\\src\\main\\java\\com\\tracko\\app\\ui\\components\\RatingBar.kt", "source_location": "L1"}, {"id": "components_ratingbar_ratingbar", "label": "RatingBar()", "file_type": "code", "source_file": "C:\\Users\\Rahul\\Documents\\Tracko\\android\\app\\src\\main\\java\\com\\tracko\\app\\ui\\components\\RatingBar.kt", "source_location": "L17"}, {"id": "components_ratingbar_displayratingbar", "label": "DisplayRatingBar()", "file_type": "code", "source_file": "C:\\Users\\Rahul\\Documents\\Tracko\\android\\app\\src\\main\\java\\com\\tracko\\app\\ui\\components\\RatingBar.kt", "source_location": "L44"}], "edges": [{"source": "c_users_rahul_documents_tracko_android_app_src_main_java_com_tracko_app_ui_components_ratingbar_kt", "target": "components_ratingbar_ratingbar", "relation": "contains", "confidence": "EXTRACTED", "source_file": "C:\\Users\\Rahul\\Documents\\Tracko\\android\\app\\src\\main\\java\\com\\tracko\\app\\ui\\components\\RatingBar.kt", "source_location": "L17", "weight": 1.0}, {"source": "c_users_rahul_documents_tracko_android_app_src_main_java_com_tracko_app_ui_components_ratingbar_kt", "target": "components_ratingbar_displayratingbar", "relation": "contains", "confidence": "EXTRACTED", "source_file": "C:\\Users\\Rahul\\Documents\\Tracko\\android\\app\\src\\main\\java\\com\\tracko\\app\\ui\\components\\RatingBar.kt", "source_location": "L44", "weight": 1.0}], "raw_calls": [{"caller_nid": "components_ratingbar_ratingbar", "callee": "Row", "is_member_call": false, "source_file": "C:\\Users\\Rahul\\Documents\\Tracko\\android\\app\\src\\main\\java\\com\\tracko\\app\\ui\\components\\RatingBar.kt", "source_location": "L27"}, {"caller_nid": "components_ratingbar_ratingbar", "callee": "IconButton", "is_member_call": false, "source_file": "C:\\Users\\Rahul\\Documents\\Tracko\\android\\app\\src\\main\\java\\com\\tracko\\app\\ui\\components\\RatingBar.kt", "source_location": "L29"}, {"caller_nid": "components_ratingbar_ratingbar", "callee": "invoke", "is_member_call": true, "source_file": "C:\\Users\\Rahul\\Documents\\Tracko\\android\\app\\src\\main\\java\\com\\tracko\\app\\ui\\components\\RatingBar.kt", "source_location": "L30"}, {"caller_nid": "components_ratingbar_ratingbar", "callee": "size", "is_member_call": true, "source_file": "C:\\Users\\Rahul\\Documents\\Tracko\\android\\app\\src\\main\\java\\com\\tracko\\app\\ui\\components\\RatingBar.kt", "source_location": "L31"}, {"caller_nid": "components_ratingbar_ratingbar", "callee": "Icon", "is_member_call": false, "source_file": "C:\\Users\\Rahul\\Documents\\Tracko\\android\\app\\src\\main\\java\\com\\tracko\\app\\ui\\components\\RatingBar.kt", "source_location": "L33"}, {"caller_nid": "components_ratingbar_ratingbar", "callee": "size", "is_member_call": true, "source_file": "C:\\Users\\Rahul\\Documents\\Tracko\\android\\app\\src\\main\\java\\com\\tracko\\app\\ui\\components\\RatingBar.kt", "source_location": "L37"}, {"caller_nid": "components_ratingbar_displayratingbar", "callee": "Row", "is_member_call": false, "source_file": "C:\\Users\\Rahul\\Documents\\Tracko\\android\\app\\src\\main\\java\\com\\tracko\\app\\ui\\components\\RatingBar.kt", "source_location": "L53"}, {"caller_nid": "components_ratingbar_displayratingbar", "callee": "Icon", "is_member_call": false, "source_file": "C:\\Users\\Rahul\\Documents\\Tracko\\android\\app\\src\\main\\java\\com\\tracko\\app\\ui\\components\\RatingBar.kt", "source_location": "L55"}, {"caller_nid": "components_ratingbar_displayratingbar", "callee": "toInt", "is_member_call": true, "source_file": "C:\\Users\\Rahul\\Documents\\Tracko\\android\\app\\src\\main\\java\\com\\tracko\\app\\ui\\components\\RatingBar.kt", "source_location": "L57"}, {"caller_nid": "components_ratingbar_displayratingbar", "callee": "size", "is_member_call": true, "source_file": "C:\\Users\\Rahul\\Documents\\Tracko\\android\\app\\src\\main\\java\\com\\tracko\\app\\ui\\components\\RatingBar.kt", "source_location": "L63"}]}