{"nodes": [{"id": "c_users_rahul_documents_tracko_android_app_src_main_java_com_tracko_app_trackoapp_kt", "label": "TrackoApp.kt", "file_type": "code", "source_file": "C:\\Users\\Rahul\\Documents\\Tracko\\android\\app\\src\\main\\java\\com\\tracko\\app\\TrackoApp.kt", "source_location": "L1"}, {"id": "app_trackoapp_trackoapp", "label": "TrackoApp", "file_type": "code", "source_file": "C:\\Users\\Rahul\\Documents\\Tracko\\android\\app\\src\\main\\java\\com\\tracko\\app\\TrackoApp.kt", "source_location": "L9"}], "edges": [{"source": "c_users_rahul_documents_tracko_android_app_src_main_java_com_tracko_app_trackoapp_kt", "target": "app_trackoapp_trackoapp", "relation": "contains", "confidence": "EXTRACTED", "source_file": "C:\\Users\\Rahul\\Documents\\Tracko\\android\\app\\src\\main\\java\\com\\tracko\\app\\TrackoApp.kt", "source_location": "L9", "weight": 1.0}], "raw_calls": []}